create_flask_api/__init__.py
create_flask_api/__main__.py
create_flask_api/build.py
create_flask_api/project.py
create_flask_api/styles.py
create_flask_api/assets/__init__.py
create_flask_api/assets/commands/__init__.py
create_flask_api/assets/commands/app_commands.py
create_flask_api/assets/commands/auth_commands.py
create_flask_api/assets/commands/ma_commands.py
create_flask_api/assets/commands/migration_commands.py
create_flask_api/assets/commands/test_commands.py
create_flask_api/assets/corrections/__init__.py
create_flask_api/assets/corrections/auth_fix.py
create_flask_api/assets/corrections/heroku_fix.py
create_flask_api/assets/corrections/ma_correction.py
create_flask_api/assets/file_paths/__init__.py
create_flask_api/assets/file_paths/app_paths.py
create_flask_api/assets/file_paths/auth_paths.py
create_flask_api/assets/file_paths/git_paths.py
create_flask_api/assets/file_paths/heroku_paths.py
create_flask_api/assets/file_paths/ma_paths.py
create_flask_api/assets/file_paths/migration_paths.py
create_flask_api/assets/file_paths/model_paths.py
create_flask_api/assets/file_paths/serializer_path.py
create_flask_api/assets/file_paths/service_paths.py
create_flask_api/assets/file_paths/test_paths.py
create_flask_api/assets/file_paths/view_paths.py
create_flask_api/assets/questions/__init__.py
create_flask_api/assets/questions/auth_questions.py
create_flask_api/assets/questions/database_questions.py
create_flask_api/assets/questions/git_questions.py
create_flask_api/assets/questions/heroku_questions.py
create_flask_api/assets/questions/ma_questions.py
create_flask_api/assets/questions/migration_questions.py
create_flask_api/assets/questions/test_questions.py
create_flask_api/assets/templates/__init__.py
create_flask_api/assets/templates/app/__init__.py
create_flask_api/assets/templates/app/commands
create_flask_api/assets/templates/app/config
create_flask_api/assets/templates/app/configurations
create_flask_api/assets/templates/app/create_app
create_flask_api-0.0.7.dist-info/LICENSE.txt
create_flask_api-0.0.7.dist-info/METADATA
create_flask_api-0.0.7.dist-info/WHEEL
create_flask_api-0.0.7.dist-info/entry_points.txt
create_flask_api-0.0.7.dist-info/top_level.txt
create_flask_api-0.0.7.dist-info/RECORD
