Metadata-Version: 2.1
Name: create-flask-api
Version: 0.0.7
Summary: This is a create-react-app analog that creates a base Flask Aplication structure with boilerplates.
Home-page: UNKNOWN
Author: Pedro Henrique Germano Silva
Author-email: pedrohenriquegs2001@gmail.com
License: UNKNOWN
Platform: UNKNOWN
Requires-Python: >=3.7,<4.0
Requires-Dist: pyfiglet (<0.9,>=0.8.post1)
Requires-Dist: PyInquirer (<2.0.0,>=1.0.3)
Requires-Dist: toml (<0.11.0,>=0.10.1)
